{
  "timestamp": "20250803_233820",
  "num_runs": 10,
  "results": [
    {
      "success": false,
      "steps": 50000,
      "visited_count": 765,
      "coverage": 60.094265514532594,
      "elapsed_time": 0.7012341022491455
    },
    {
      "success": true,
      "steps": 16048,
      "visited_count": 405,
      "coverage": 31.739811912225708,
      "elapsed_time": 0.226409912109375
    },
    {
      "success": true,
      "steps": 13280,
      "visited_count": 231,
      "coverage": 18.174665617623916,
      "elapsed_time": 0.18927001953125
    },
    {
      "success": true,
      "steps": 16002,
      "visited_count": 460,
      "coverage": 36.1351139041634,
      "elapsed_time": 0.22278189659118652
    },
    {
      "success": false,
      "steps": 50000,
      "visited_count": 533,
      "coverage": 42.10110584518168,
      "elapsed_time": 0.6931169033050537
    },
    {
      "success": false,
      "steps": 50000,
      "visited_count": 616,
      "coverage": 48.46577498033045,
      "elapsed_time": 0.7062568664550781
    },
    {
      "success": false,
      "steps": 50000,
      "visited_count": 389,
      "coverage": 30.50980392156863,
      "elapsed_time": 0.7148909568786621
    },
    {
      "success": false,
      "steps": 50000,
      "visited_count": 202,
      "coverage": 15.880503144654087,
      "elapsed_time": 0.6990001201629639
    },
    {
      "success": true,
      "steps": 39748,
      "visited_count": 556,
      "coverage": 43.64207221350079,
      "elapsed_time": 0.5510063171386719
    },
    {
      "success": false,
      "steps": 50000,
      "visited_count": 408,
      "coverage": 32.050274941084055,
      "elapsed_time": 0.6927499771118164
    }
  ]
}