[
  {
    "text": "At (9,2) took up got success",
    "c_value": 0.5,
    "timestamp": null,
    "metadata": {
      "id": "datastore_test_25x25_run2_ep_1938",
      "pos": [
        9,
        2
      ],
      "action": "up",
      "result": "success",
      "reached_goal": false,
      "step": 1938,
      "maze_size": [
        25,
        25
      ],
      "experiment_id": "datastore_test_25x25_run2"
    },
    "vec": [
      0.24632124649139475,
      0.054738054775865505,
      -0.6842256846983188,
      0.6842256846983188,
      0.0,
      0.0
    ]
  }
]